tree_sitter_fortran/__init__.py
tree_sitter_fortran/__init__.pyi
tree_sitter_fortran/_binding.abi3.so
tree_sitter_fortran/binding.c
tree_sitter_fortran/py.typed
tree_sitter_fortran/queries/folds.scm
tree_sitter_fortran/queries/highlights.scm
tree_sitter_fortran/queries/indents.scm
tree_sitter_fortran-0.5.1.dist-info/LICENSE
tree_sitter_fortran-0.5.1.dist-info/METADATA
tree_sitter_fortran-0.5.1.dist-info/WHEEL
tree_sitter_fortran-0.5.1.dist-info/top_level.txt
tree_sitter_fortran-0.5.1.dist-info/RECORD
