Metadata-Version: 2.2
Name: tree-sitter-fortran
Version: 0.5.1
Summary: Fortran grammar for tree-sitter
License: MIT
Project-URL: Homepage, https://github.com/stadelmanma/tree-sitter-fortran
Keywords: incremental,parsing,tree-sitter,fortran
Classifier: Intended Audience :: Developers
Classifier: License :: OSI Approved :: MIT License
Classifier: Topic :: Software Development :: Compilers
Classifier: Topic :: Text Processing :: Linguistic
Classifier: Typing :: Typed
Requires-Python: >=3.9
License-File: LICENSE
Provides-Extra: core
Requires-Dist: tree-sitter~=0.21; extra == "core"
